ghupdatesecret/__init__.py
ghupdatesecret/ghupdatesecret.py
ghupdatesecret-0.0.2.dist-info/LICENSE
ghupdatesecret-0.0.2.dist-info/METADATA
ghupdatesecret-0.0.2.dist-info/WHEEL
ghupdatesecret-0.0.2.dist-info/entry_points.txt
ghupdatesecret-0.0.2.dist-info/top_level.txt
ghupdatesecret-0.0.2.dist-info/RECORD
