Metadata-Version: 2.1
Name: ghupdatesecret
Version: 0.0.2
Summary: A command-line utility to update GitHub repository secrets.
Home-page: https://github.com/jansky/ghupdatesecret
Author: Ian Duncan
Author-email: janskykd@gmail.com
License: UNKNOWN
Platform: UNKNOWN
Classifier: Programming Language :: Python :: 3
Classifier: License :: OSI Approved :: MIT License
Classifier: Operating System :: OS Independent
Classifier: Topic :: Software Development :: Version Control
Classifier: Topic :: Software Development :: Version Control :: Git
Requires-Python: >=3.6
Requires-Dist: requests (>=2.24.0)
Requires-Dist: pynacl (>=1.4.0)
